gecko/__init__.py
gecko/_cldr.py
gecko/_dfbitlookup.py
gecko/_typedefs.py
gecko/generator.py
gecko/mutator.py
gecko_syndata-0.6.4.dist-info/LICENSE
gecko_syndata-0.6.4.dist-info/METADATA
gecko_syndata-0.6.4.dist-info/WHEEL
gecko_syndata-0.6.4.dist-info/RECORD
