Metadata-Version: 2.1
Name: gecko-syndata
Version: 0.6.4
Summary: Generation and mutation of realistic data at scale.
Home-page: https://github.com/ul-mds/gecko
License: MIT
Keywords: data science,data generation,data mutation
Author: Maximilian Jugl
Author-email: Maximilian.Jugl@medizin.uni-leipzig.de
Requires-Python: >=3.9,<4.0
Classifier: Development Status :: 4 - Beta
Classifier: Environment :: Console
Classifier: Intended Audience :: Developers
Classifier: Intended Audience :: Education
Classifier: Intended Audience :: Science/Research
Classifier: License :: OSI Approved :: MIT License
Classifier: Programming Language :: Python :: 3
Classifier: Programming Language :: Python :: 3.9
Classifier: Programming Language :: Python :: 3.10
Classifier: Programming Language :: Python :: 3.11
Classifier: Programming Language :: Python :: 3.12
Classifier: Programming Language :: Python :: 3.13
Classifier: Topic :: Software Development :: Libraries :: Python Modules
Classifier: Topic :: Software Development :: Testing
Classifier: Topic :: Utilities
Requires-Dist: lxml (>=5.3.0,<6)
Requires-Dist: numpy (>=1.20.3,<2)
Requires-Dist: pandas (>=2.0.0,<3.0.0)
Requires-Dist: typing-extensions (>=4.0.0,<5.0.0)
Project-URL: Documentation, https://ul-mds.github.io/gecko/
Project-URL: Repository, https://github.com/ul-mds/gecko
